{
  "meta": {
    "exportedAt": "2026-02-02T11:35:00.000Z",
    "appVersion": "Mentor_data_v17"
  },
  "part": [
    {
      "id": 1300000000001,
      "name": "Финансовый директор (CFO) / Финансовый аналитик",
      "rate": 18000,
      "availableTime": 480
    },
    {
      "id": 1300000000002,
      "name": "Экономист / Специалист по планированию",
      "rate": 7000,
      "availableTime": 600
    },
    {
      "id": 1300000000003,
      "name": "Собственник / Генеральный директор",
      "rate": 0,
      "availableTime": 120,
      "excludeFromStats": true
    },
    {
      "id": 1300000000004,
      "name": "Бюджет утвержден, модель сценарного анализа готова (Финал)",
      "rate": 0,
      "availableTime": 0,
      "excludeFromStats": true
    }
  ],
  "resources": [],
  "steps": [
    {
      "id": 1300000000100,
      "uiId": 1,
      "action": "Сбор исторических данных и ретроспективный анализ",
      "respId": 1300000000002,
      "inputs": [
        "Отчет о прибылях и убытках (P&L) за прошлые периоды",
        "Отчет о движении денежных средств (Cash Flow)"
      ],
      "outputs": [
        "База данных по драйверам выручки и структуре затрат",
        "Анализ отклонений (Plan-Fact)"
      ],
      "timeMin": 480,
      "timeMax": 1440,
      "respIds": [
        1300000000002
      ]
    },
    {
      "id": 1300000000101,
      "uiId": 2,
      "action": "Определение стратегических целей и KPI на период",
      "respId": 1300000000003,
      "inputs": [
        "Стратегия развития компании",
        "Рыночные бенчмарки и макроэкономические прогнозы"
      ],
      "outputs": [
        "Целевые показатели (EBITDA, Чистая прибыль, ROI)",
        "Лимиты операционных расходов (OPEX)"
      ],
      "timeMin": 120,
      "timeMax": 480,
      "respIds": [
        1300000000003,
        1300000000001
      ]
    },
    {
      "id": 1300000000102,
      "uiId": 3,
      "action": "Построение финансовой модели и сценарное моделирование",
      "respId": 1300000000001,
      "inputs": [
        "План продаж от коммерческого департамента",
        "Инвестиционный план (CAPEX)"
      ],
      "outputs": [
        "Динамическая финансовая модель (Excel/ERP)",
        "Сценарии: Оптимистичный, Базовый, Пессимистичный"
      ],
      "timeMin": 960,
      "timeMax": 2880,
      "respIds": [
        1300000000001
      ]
    },
    {
      "id": 1300000000103,
      "uiId": 4,
      "action": "Формирование платежного календаря и устранение кассовых разрывов",
      "respId": 1300000000002,
      "inputs": [
        "График платежей по договорам",
        "Ожидаемые поступления от дебиторов"
      ],
      "outputs": [
        "Прогноз ликвидности",
        "Рекомендации по привлечению финансирования/факторингу"
      ],
      "timeMin": 240,
      "timeMax": 720,
      "respIds": [
        1300000000002,
        1300000000001
      ]
    },
    {
      "id": 1300000000104,
      "uiId": 5,
      "action": "Утверждение бюджета и настройка системы контроля",
      "respId": 1300000000003,
      "inputs": [
        "Финальный проект бюджета",
        "Регламент бюджетного контроля"
      ],
      "outputs": [
        "Утвержденный годовой бюджет",
        "Дашборд мониторинга ключевых показателей"
      ],
      "timeMin": 60,
      "timeMax": 240,
      "respIds": [
        1300000000003,
        1300000000001
      ]
    }
  ],
  "structure": [
    {
      "id": 1300000000200,
      "type": "group",
      "logic": "SEQ",
      "children": [
        {
          "id": 1300000000201,
          "type": "step",
          "stepId": 1300000000100
        },
        {
          "id": 1300000000202,
          "type": "step",
          "stepId": 1300000000101
        }
      ]
    },
    {
      "id": 1300000000203,
      "type": "group",
      "logic": "SEQ",
      "children": [
        {
          "id": 1300000000204,
          "type": "step",
          "stepId": 1300000000102
        }
      ]
    },
    {
      "id": 1300000000205,
      "type": "group",
      "logic": "AND",
      "children": [
        {
          "id": 1300000000206,
          "type": "step",
          "stepId": 1300000000103
        },
        {
          "id": 1300000000207,
          "type": "step",
          "stepId": 1300000000104
        }
      ]
    }
  ],
  "temp": {
    "inputs": [],
    "outputs": [],
    "newStepInputs": [],
    "newStepOutputs": [],
    "editStepId": null,
    "editStepInputs": [],
    "editStepOutputs": [],
    "newStepRespIds": [
      1300000000001
    ]
  }
}

